CHANGELOG
LICENSE
MANIFEST.in
README.txt
setup.py
test_xlocal.py
tox.ini
xlocal.py
xlocal.egg-info/PKG-INFO
xlocal.egg-info/SOURCES.txt
xlocal.egg-info/dependency_links.txt
xlocal.egg-info/top_level.txt