Metadata-Version: 1.0
Name: xlocal
Version: 0.5
Summary: execution locals: killing global state (including thread locals)
Home-page: http://bitbucket.org/hpk42/xlocal/
Author: Holger Krekel
Author-email: holger.krekel@gmail.com
License: UNKNOWN
Platform: UNKNOWN
